chains/__init__.py
chains/mcp_utils.py
chains/msg_chain.py
chains/utils.py
chains/msg_chains/__init__.py
chains/msg_chains/claude_msg_chain.py
chains/msg_chains/gemini_msg_chain.py
chains/msg_chains/instructor_msg_chain.py
chains/msg_chains/mock_instructor_chain.py
chains/msg_chains/oai_msg_chain.py
chains/msg_chains/oai_msg_chain_async.py
chains/prompts/__init__.py
chains/prompts/compiled_prompt.py
chains/prompts/prompt_chain.py
chains/prompts/prompt_module.py
chains/prompts/utils/__init__.py
chains/prompts/utils/safe_eval.py
chains_py-0.2.0.dist-info/METADATA
chains_py-0.2.0.dist-info/WHEEL
chains_py-0.2.0.dist-info/top_level.txt
chains_py-0.2.0.dist-info/RECORD
