Metadata-Version: 2.4
Name: chains-py
Version: 0.2.0
Summary: A unified, chainable interface for working with multiple LLM providers
Home-page: https://github.com/ohadr/chains
Author: ohadr
Classifier: Programming Language :: Python :: 3
Classifier: License :: OSI Approved :: MIT License
Classifier: Operating System :: OS Independent
Requires-Python: >=3.7
Requires-Dist: anthropic
Requires-Dist: anthropic[bedrock]
Requires-Dist: google-generativeai>=0.3.0
Requires-Dist: openai
Requires-Dist: tenacity
Requires-Dist: appdirs
Requires-Dist: pydantic
Requires-Dist: fire
Requires-Dist: instructor
Requires-Dist: jinja2
Dynamic: author
Dynamic: classifier
Dynamic: description
Dynamic: description-content-type
Dynamic: home-page
Dynamic: requires-dist
Dynamic: requires-python
Dynamic: summary
